setup.py
gaussian_bin_dist/Binomialdistribution.py
gaussian_bin_dist/Gaussiandistribution.py
gaussian_bin_dist/Generaldistribution.py
gaussian_bin_dist/__init__.py
gaussian_bin_dist.egg-info/PKG-INFO
gaussian_bin_dist.egg-info/SOURCES.txt
gaussian_bin_dist.egg-info/dependency_links.txt
gaussian_bin_dist.egg-info/not-zip-safe
gaussian_bin_dist.egg-info/top_level.txt