Metadata-Version: 1.0
Name: gaussian-bin-dist
Version: 1.0
Summary: Gaussian distributions
Home-page: UNKNOWN
Author: Parth Mehta
Author-email: UNKNOWN
License: UNKNOWN
Platform: UNKNOWN
